anywise/Interface.py
anywise/__init__.py
anywise/_cli.py
anywise/_ds.py
anywise/_visitor.py
anywise/anywise.py
anywise/errors.py
anywise/guard.py
anywise/py.typed
anywise/registry.py
anywise/runtime.py
anywise/strategies.py
anywise/integration/__init__.py
anywise/integration/fastapi.py
anywise/messages/__init__.py
anywise/messages/eventstore.py
anywise/messages/model.py
anywise/messages/table.py
anywise/sink/__init__.py
anywise/source/__init__.py
anywise/utils/_errordoc.py
anywise/utils/query.py
anywise-0.1.9.dist-info/METADATA
anywise-0.1.9.dist-info/WHEEL
anywise-0.1.9.dist-info/licenses/LICENSE
anywise-0.1.9.dist-info/RECORD
