Metadata-Version: 2.4
Name: anywise
Version: 0.1.9
Summary: Anywise let you write your application anywise
Author-email: raceychan <raceychan@gmail.com>
License-File: LICENSE
Requires-Python: >=3.12
Requires-Dist: ididi>=1.3.0
